transpire/__init__.py
transpire/__main__.py
transpire/helm.py
transpire/internal/argocd.py
transpire/internal/cli/__init__.py
transpire/internal/cli/bootstrap.py
transpire/internal/cli/dev.py
transpire/internal/cli/image.py
transpire/internal/cli/obj.py
transpire/internal/cli/secrets.py
transpire/internal/config.py
transpire/internal/context.py
transpire/internal/helm.py
transpire/internal/postprocessor.py
transpire/internal/render.py
transpire/internal/secrets/__init__.py
transpire/internal/secrets/vault.py
transpire/internal/surgery.py
transpire/internal/validation.py
transpire/manifestlike.py
transpire/py.typed
transpire/resources/__init__.py
transpire/resources/base.py
transpire/resources/configmap.py
transpire/resources/deployment.py
transpire/resources/ingress.py
transpire/resources/secret.py
transpire/resources/service.py
transpire/surgery.py
transpire/types.py
transpire/utils.py
transpire-0.2.0.dist-info/LICENSE
transpire-0.2.0.dist-info/METADATA
transpire-0.2.0.dist-info/WHEEL
transpire-0.2.0.dist-info/entry_points.txt
transpire-0.2.0.dist-info/RECORD
